glartifacts/__init__.py
glartifacts/__main__.py
glartifacts/artifacts.py
glartifacts/ciyaml.py
glartifacts/config.py
glartifacts/errors.py
glartifacts/projects.py
glartifacts/utils.py
glartifacts/version.py
glartifacts/gitaly/__init__.py
glartifacts/gitaly/client.py
glartifacts/gitaly/proto/__init__.py
glartifacts/gitaly/proto/blob_pb2.py
glartifacts/gitaly/proto/blob_pb2_grpc.py
glartifacts/gitaly/proto/cleanup_pb2.py
glartifacts/gitaly/proto/cleanup_pb2_grpc.py
glartifacts/gitaly/proto/commit_pb2.py
glartifacts/gitaly/proto/commit_pb2_grpc.py
glartifacts/gitaly/proto/conflicts_pb2.py
glartifacts/gitaly/proto/conflicts_pb2_grpc.py
glartifacts/gitaly/proto/diff_pb2.py
glartifacts/gitaly/proto/diff_pb2_grpc.py
glartifacts/gitaly/proto/errors_pb2.py
glartifacts/gitaly/proto/errors_pb2_grpc.py
glartifacts/gitaly/proto/hook_pb2.py
glartifacts/gitaly/proto/hook_pb2_grpc.py
glartifacts/gitaly/proto/internal_pb2.py
glartifacts/gitaly/proto/internal_pb2_grpc.py
glartifacts/gitaly/proto/lint_pb2.py
glartifacts/gitaly/proto/lint_pb2_grpc.py
glartifacts/gitaly/proto/namespace_pb2.py
glartifacts/gitaly/proto/namespace_pb2_grpc.py
glartifacts/gitaly/proto/objectpool_pb2.py
glartifacts/gitaly/proto/objectpool_pb2_grpc.py
glartifacts/gitaly/proto/operations_pb2.py
glartifacts/gitaly/proto/operations_pb2_grpc.py
glartifacts/gitaly/proto/praefect_pb2.py
glartifacts/gitaly/proto/praefect_pb2_grpc.py
glartifacts/gitaly/proto/ref_pb2.py
glartifacts/gitaly/proto/ref_pb2_grpc.py
glartifacts/gitaly/proto/remote_pb2.py
glartifacts/gitaly/proto/remote_pb2_grpc.py
glartifacts/gitaly/proto/repository_pb2.py
glartifacts/gitaly/proto/repository_pb2_grpc.py
glartifacts/gitaly/proto/server_pb2.py
glartifacts/gitaly/proto/server_pb2_grpc.py
glartifacts/gitaly/proto/shared_pb2.py
glartifacts/gitaly/proto/shared_pb2_grpc.py
glartifacts/gitaly/proto/smarthttp_pb2.py
glartifacts/gitaly/proto/smarthttp_pb2_grpc.py
glartifacts/gitaly/proto/ssh_pb2.py
glartifacts/gitaly/proto/ssh_pb2_grpc.py
glartifacts-2.4.0.dist-info/LICENSE
glartifacts-2.4.0.dist-info/METADATA
glartifacts-2.4.0.dist-info/WHEEL
glartifacts-2.4.0.dist-info/entry_points.txt
glartifacts-2.4.0.dist-info/top_level.txt
glartifacts-2.4.0.dist-info/RECORD
