Metadata-Version: 2.1
Name: glartifacts
Version: 2.4.0
Summary: Tools for managing GitLab CI build artifacts
Home-page: https://gitlab.com/haboustak/gitlab-artifact-tools
Author: Mike Haboustak
Author-email: haboustak@gmail.com
License: MIT
Keywords: GitLab
Classifier: Development Status :: 4 - Beta
Classifier: Environment :: Console
Classifier: Intended Audience :: System Administrators
Classifier: License :: OSI Approved :: MIT License
Classifier: Natural Language :: English
Classifier: Operating System :: POSIX :: Linux
Classifier: Programming Language :: Python :: 3 :: Only
Classifier: Topic :: Utilities
License-File: LICENSE
Requires-Dist: grpcio (>=1.15.0)
Requires-Dist: protobuf (>=3.6.1)
Requires-Dist: psycopg2 (>=2.6)
Requires-Dist: pyyaml (>=3.11)
